textbook_assembler/__init__.py
textbook_assembler/__main__.py
textbook_assembler/main.py
textbook_assembler/tests/__init__.py
textbook_assembler/tests/test_data.py
textbook_assembler/tests/test_latex.py
textbook_assembler/tests/test_main.py
textbook_assembler/tests/test_make_text.py
textbook_assembler/tests/test_references.py
textbook_assembler/utils/__init__.py
textbook_assembler/utils/constants.py
textbook_assembler/utils/data.py
textbook_assembler/utils/latex.py
textbook_assembler/utils/make_text.py
textbook_assembler/utils/references.py
textbook_assembler-1.0.4.dist-info/METADATA
textbook_assembler-1.0.4.dist-info/WHEEL
textbook_assembler-1.0.4.dist-info/top_level.txt
textbook_assembler-1.0.4.dist-info/RECORD
