Metadata-Version: 2.1
Name: textbook-assembler
Version: 1.0.4
Summary: Assembles a PDF textbook from sources and adds citations
Home-page: https://github.com/jessegrabowski/textbook_assembler
Author: Jesse Grabowski
Author-email: jessegrabowski@gmail.com
Requires-Dist: pyyaml
Requires-Dist: unidecode
Requires-Dist: pypdf
Requires-Dist: pylatex
Requires-Dist: pandas
Requires-Dist: bibtexparser
